setup.py
zbbert/Output.py
zbbert/PredictFromSavedModel.py
zbbert/TextProcess.py
zbbert/__init__.py
zbbert/bertmodel.py
zbbert/test.py
zbbert.egg-info/PKG-INFO
zbbert.egg-info/SOURCES.txt
zbbert.egg-info/dependency_links.txt
zbbert.egg-info/requires.txt
zbbert.egg-info/top_level.txt