Metadata-Version: 1.0
Name: zbbert
Version: 0.1
Summary: Python API for NER task
Home-page: UNKNOWN
Author: wgh
Author-email: 1272599042@qq.com
License: UNKNOWN
Platform: UNKNOWN
